fedbadges/__init__.py
fedbadges/aio.py
fedbadges/cached.py
fedbadges/consumer.py
fedbadges/fas.py
fedbadges/manual/__init__.py
fedbadges/manual/badges_dev.py
fedbadges/manual/group_membership.py
fedbadges/manual/libravatar.py
fedbadges/manual/lifecycle.py
fedbadges/manual/mirror.py
fedbadges/manual/utils.py
fedbadges/rules.py
fedbadges/rulesrepo.py
fedbadges/utils.py
fedbadges-2.2.0.dist-info/LICENSE
fedbadges-2.2.0.dist-info/METADATA
fedbadges-2.2.0.dist-info/WHEEL
fedbadges-2.2.0.dist-info/entry_points.txt
fedbadges-2.2.0.dist-info/RECORD
