Metadata-Version: 2.1
Name: fedbadges
Version: 2.2.0
Summary: Fedora Messaging consumer for awarding open badges
Home-page: https://github.com/fedora-infra/fedbadges
License: GPL-2.0-or-later
Keywords: fedora
Author: Fedora Infrastructure
Author-email: admin@fedoraproject.org
Requires-Python: >=3.10,<4.0
Classifier: License :: OSI Approved :: GNU General Public License v2 or later (GPLv2+)
Classifier: Operating System :: POSIX :: Linux
Classifier: Programming Language :: Python :: 3
Classifier: Programming Language :: Python :: 3.10
Classifier: Programming Language :: Python :: 3.11
Classifier: Programming Language :: Python :: 3.12
Classifier: Programming Language :: Python :: 3.9
Provides-Extra: redis
Provides-Extra: schemas
Requires-Dist: anitya-schema ; extra == "schemas"
Requires-Dist: backoff (>=2.2.1,<3.0.0)
Requires-Dist: bodhi-messages ; extra == "schemas"
Requires-Dist: bugzilla2fedmsg-schema ; extra == "schemas"
Requires-Dist: ci-messages ; extra == "schemas"
Requires-Dist: click (>=8.0.0,<9.0.0)
Requires-Dist: copr-messaging ; extra == "schemas"
Requires-Dist: datanommer-models (>=1.4.0,<2.0.0)
Requires-Dist: discourse2fedmsg-messages ; extra == "schemas"
Requires-Dist: dogpile-cache (>=1.3.2,<2.0.0)
Requires-Dist: fasjson-client (>=1.0.8,<2.0.0)
Requires-Dist: fedocal-messages ; extra == "schemas"
Requires-Dist: fedora-elections-messages ; extra == "schemas"
Requires-Dist: fedora-messaging (>=3.6.0,<4.0.0)
Requires-Dist: fedora-messaging-git-hook-messages ; extra == "schemas"
Requires-Dist: fedora-messaging-the-new-hotness-schema ; extra == "schemas"
Requires-Dist: fedora-planet-messages ; extra == "schemas"
Requires-Dist: fedorainfra-ansible-messages ; extra == "schemas"
Requires-Dist: fmn-messages ; extra == "schemas"
Requires-Dist: kerneltest-messages (>=1.0.0,<2.0.0) ; extra == "schemas"
Requires-Dist: koji-fedoramessaging-messages (>=1.2.2,<2.0.0) ; extra == "schemas"
Requires-Dist: koschei-messages ; extra == "schemas"
Requires-Dist: maubot-fedora-messages ; extra == "schemas"
Requires-Dist: mdapi-messages ; extra == "schemas"
Requires-Dist: mediawiki-messages ; extra == "schemas"
Requires-Dist: meetbot-messages ; extra == "schemas"
Requires-Dist: noggin-messages ; extra == "schemas"
Requires-Dist: nuancier-messages ; extra == "schemas"
Requires-Dist: pagure-messages ; extra == "schemas"
Requires-Dist: psutil (>=5.9.8,<7.0.0)
Requires-Dist: pydantic-settings (>=2.0.2,<3.0.0)
Requires-Dist: pymemcache (>=4.0.0,<5.0.0)
Requires-Dist: pyyaml (>=6.0.1,<7.0.0)
Requires-Dist: redis (>=5.0.4,<6.0.0) ; extra == "redis"
Requires-Dist: requests (>=2.31.0,<3.0.0)
Requires-Dist: requests-ratelimiter (>=0.6.0,<0.7.0)
Requires-Dist: tahrir-api (>=1.0.0,<2.0.0)
Requires-Dist: tahrir-messages ; extra == "schemas"
Project-URL: Repository, https://github.com/fedora-infra/fedbadges
